pubtools/executors.py
pubtools/_executors/__init__.py
pubtools/_executors/helpers.py
pubtools/_executors/skopeo.py
pubtools_executors-0.0.3.dist-info/LICENSE
pubtools_executors-0.0.3.dist-info/METADATA
pubtools_executors-0.0.3.dist-info/WHEEL
pubtools_executors-0.0.3.dist-info/dependency_links.txt
pubtools_executors-0.0.3.dist-info/top_level.txt
pubtools_executors-0.0.3.dist-info/RECORD
